{"@context":"","user":"rossella","demographics":{"name":[],"location":[],"image":[],"email":[],"gender":[],"language":[],"work":[],"industry":[],"height":[],"weight":[],"dateOfBirth":[],"country":[],"device":[]},"affects":[],"behaviors":{"fromText":[],"fromActivity":[]},"cognitiveAspects":{"personalities":[],"empathies":[]},"interests":[{"source":"music_preference","value":"Like:Genre:latin christian latin worship vbs","confidence":1,"timestamp":1610785622915},{"source":"music_preference","value":"Like:Artist:gu\u00e8 pequeno","confidence":1,"timestamp":1610785622915},{"source":"news_preference","value":"Like:gu\u00e8 pequeno","confidence":0.56,"timestamp":1610785622915},{"source":"video_preference","value":"Like:latin christian latin worship vbs","confidence":0.5,"timestamp":1610785622915},{"source":"music_preference","value":"Like:Genre:italian hip hop italian indie pop trap italiana","confidence":1,"timestamp":1610785649563},{"source":"music_preference","value":"Like:Artist:capo plaza","confidence":1,"timestamp":1610785649563},{"source":"news_preference","value":"Like:capo plaza","confidence":0.56,"timestamp":1610785649563},{"source":"video_preference","value":"Like:italian hip hop italian indie pop trap italiana","confidence":0.5,"timestamp":1610785649563},{"source":"music_preference","value":"Like:Genre:cumbia pop","confidence":1,"timestamp":1610785674410},{"source":"music_preference","value":"Like:Artist:ana mena","confidence":1,"timestamp":1610785674410},{"source":"news_preference","value":"Like:ana mena","confidence":0.56,"timestamp":1610785674410},{"source":"video_preference","value":"Like:cumbia pop","confidence":0.5,"timestamp":1610785674410},{"source":"music_preference","value":"Like:Artist:luciano ligabue","confidence":1,"timestamp":1610785679672},{"source":"news_preference","value":"Like:luciano ligabue","confidence":0.56,"timestamp":1610785679672},{"source":"video_preference","value":"Like:luciano ligabue","confidence":0.5,"timestamp":1610785679672},{"source":"music_preference","value":"Like:Genre:classic italian pop italian adult pop","confidence":1,"timestamp":1610785691469},{"source":"music_preference","value":"Like:Artist:vasco rossi","confidence":1,"timestamp":1610785691469},{"source":"news_preference","value":"Like:vasco rossi","confidence":0.56,"timestamp":1610785691469},{"source":"video_preference","value":"Like:classic italian pop italian adult pop","confidence":0.5,"timestamp":1610785691469},{"source":"music_preference","value":"Like:Genre:italian hip hop","confidence":1,"timestamp":1610785702832},{"source":"music_preference","value":"Like:Artist:gemitaiz","confidence":1,"timestamp":1610785702832},{"source":"news_preference","value":"Like:gemitaiz","confidence":0.56,"timestamp":1610785702832},{"source":"video_preference","value":"Like:italian hip hop","confidence":0.5,"timestamp":1610785702832},{"source":"music_preference","value":"Like:Genre:italian adult pop italian indie pop italian pop rap napoletano rome indie","confidence":1,"timestamp":1610785718650},{"source":"music_preference","value":"Like:Artist:marracash","confidence":1,"timestamp":1610785718650},{"source":"news_preference","value":"Like:marracash","confidence":0.56,"timestamp":1610785718650},{"source":"video_preference","value":"Like:italian adult pop italian indie pop italian pop rap napoletano rome indie","confidence":0.5,"timestamp":1610785718650},{"source":"music_preference","value":"Like:Genre:pop","confidence":0.5,"timestamp":1610785866347},{"source":"music_preference","value":"Like:Song:bling bling","confidence":1,"timestamp":1610785732066},{"source":"music_preference","value":"Like:Artist:b.g.","confidence":0.7,"timestamp":1610785732066},{"source":"news_preference","value":"Like:b.g.","confidence":0.35,"timestamp":1610785732066},{"source":"video_preference","value":"Like:bling bling","confidence":0.5,"timestamp":1610785732066},{"source":"video_preference","value":"Like:b.g.","confidence":0.5,"timestamp":1610785732066},{"source":"music_preference","value":"Like:Song:baby","confidence":1,"timestamp":1610785787508},{"source":"music_preference","value":"Like:Artist:brett eldredge","confidence":0.7,"timestamp":1610785787508},{"source":"news_preference","value":"Like:brett eldredge","confidence":0.35,"timestamp":1610785787508},{"source":"video_preference","value":"Like:baby","confidence":0.5,"timestamp":1610785787508},{"source":"music_preference","value":"Like:Artist:j balvin","confidence":1,"timestamp":1610785829219},{"source":"news_preference","value":"Like:j balvin","confidence":0.56,"timestamp":1610785829219},{"source":"video_preference","value":"Like:j balvin","confidence":0.5,"timestamp":1610785829219},{"source":"music_preference","value":"Like:Genre:hiphop","confidence":0.5,"timestamp":1610785846835},{"source":"music_preference","value":"Like:Song:superclassico","confidence":1,"timestamp":1610785846835},{"source":"music_preference","value":"Like:Artist:ernia","confidence":0.7,"timestamp":1610785846835},{"source":"news_preference","value":"Like:ernia","confidence":0.35,"timestamp":1610785846835},{"source":"video_preference","value":"Like:superclassico","confidence":0.5,"timestamp":1610785846835},{"source":"video_preference","value":"Like:ernia","confidence":0.5,"timestamp":1610785846835},{"source":"music_preference","value":"Like:Song:bella storia","confidence":1,"timestamp":1610785866347},{"source":"music_preference","value":"Like:Artist:fedez","confidence":0.7,"timestamp":1610785866347},{"source":"news_preference","value":"Like:fedez","confidence":0.35,"timestamp":1610785866347},{"source":"video_preference","value":"Like:bella storia","confidence":0.5,"timestamp":1610785866347},{"source":"video_preference","value":"Like:fedez","confidence":0.5,"timestamp":1610785866347}],"telegramProfile":[],"physicalStates":{"heart":[],"sleep":[],"food":[],"body":[],"diagnosis":[],"analysis":[],"therapies":[],"medicalAreas":[],"medicalVisits":[],"diseases":[],"hospitalizations":[]},"socialRelations":[]}